README.md
setup.py
zrq_pkg/HMM.py
zrq_pkg/LogisticRegression.py
zrq_pkg/__init__.py
zrq_pkg/helloworld.py
zrq_pkg/timeseries1231.py
zrq_pkg.egg-info/PKG-INFO
zrq_pkg.egg-info/SOURCES.txt
zrq_pkg.egg-info/dependency_links.txt
zrq_pkg.egg-info/top_level.txt