Metadata-Version: 2.1
Name: zrq-pkg
Version: 0.0.3
Summary: PyPI Tutorial
Home-page: https://github.com/
Author: zrq
Author-email: zhang_rq@neusoft.com
License: UNKNOWN
Platform: UNKNOWN
Classifier: Programming Language :: Python :: 3
Classifier: License :: OSI Approved :: MIT License
Classifier: Operating System :: OS Independent
